oncodriveclustl/__init__.py
oncodriveclustl/main.py
oncodriveclustl/data/CGC_all_Oct15_10_29_09_2018.tsv
oncodriveclustl/parsers/__init__.py
oncodriveclustl/parsers/vcf.py
oncodriveclustl/utils/__init__.py
oncodriveclustl/utils/analyticalpval.py
oncodriveclustl/utils/cluster_plot.py
oncodriveclustl/utils/clustering.py
oncodriveclustl/utils/exceptions.py
oncodriveclustl/utils/parsing.py
oncodriveclustl/utils/postprocessing.py
oncodriveclustl/utils/qq_plot.py
oncodriveclustl/utils/run.py
oncodriveclustl/utils/score.py
oncodriveclustl/utils/smoothing.py
oncodriveclustl-1.2.0.dist-info/METADATA
oncodriveclustl-1.2.0.dist-info/WHEEL
oncodriveclustl-1.2.0.dist-info/entry_points.txt
oncodriveclustl-1.2.0.dist-info/licenses/LICENSE
oncodriveclustl-1.2.0.dist-info/RECORD
