Metadata-Version: 2.3
Name: oncodriveclustl
Version: 1.2.0
Summary: OncodriveCLUSTL is a clustering method to identify cancer drivers
Author-email: "BBGLab (Barcelona Biomedical Genomics Lab)" <bbglab@irbbarcelona.org>
License: OncodriveClustl is the property of the Institute for Research in Biomedicine (IRB Barcelona), which hold the copyright thereto.
Requires-Python: <3.13,>=3.10
Requires-Dist: bgparsers==0.10
Requires-Dist: bgreference==0.7
Requires-Dist: bgsignature==0.2
Requires-Dist: click==8.1.7
Requires-Dist: daiquiri==3.2.5.1
Requires-Dist: intervaltree==3.1.0
Requires-Dist: matplotlib==3.9.2
Requires-Dist: numpy==2.0.1
Requires-Dist: pandas==2.2.2
Requires-Dist: scikit-learn==1.5.1
Requires-Dist: scipy==1.14.0
Requires-Dist: statsmodels==0.14.2
Requires-Dist: tqdm==4.66.5
